baric/__init__.py
baric/baricentric.py
baric-0.2.dist-info/METADATA
baric-0.2.dist-info/WHEEL
baric-0.2.dist-info/top_level.txt
baric-0.2.dist-info/RECORD
