Metadata-Version: 2.1
Name: baric
Version: 0.2
Summary: This is baricentric
Home-page: https://github.com/std
Author: K Antonov
Author-email: kirill_antonov1111@mail.ru
License: BSD 2-clause
Platform: UNKNOWN
